bunny_lab/__init__.py
bunny_lab/__main__.py
bunny_lab/api.py
bunny_lab/bunny_names.txt
bunny_lab/levels.py
bunny_lab/logic.py
bunny_lab/names.py
bunny_lab/server.py
bunny_lab-0.0.3.dist-info/LICENSE
bunny_lab-0.0.3.dist-info/METADATA
bunny_lab-0.0.3.dist-info/WHEEL
bunny_lab-0.0.3.dist-info/top_level.txt
bunny_lab-0.0.3.dist-info/RECORD
