Metadata-Version: 2.1
Name: bunny-lab
Version: 0.0.3
Summary: An interactive Python quest to save the bunnies.
Home-page: https://github.com/simonpf/bunny_lab
Author: Simon Pfreundschuh
Author-email: simon.pfreundschuh@chalmers.se
License: UNKNOWN
Platform: UNKNOWN
Classifier: Programming Language :: Python :: 3
Classifier: License :: OSI Approved :: MIT License
Requires-Python: >=3.6
